nova_steward/__init__.py
nova_steward/core.py
nova_steward-1.0.1.dist-info/METADATA
nova_steward-1.0.1.dist-info/WHEEL
nova_steward-1.0.1.dist-info/entry_points.txt
nova_steward-1.0.1.dist-info/top_level.txt
nova_steward-1.0.1.dist-info/RECORD
