Metadata-Version: 2.4
Name: nova-steward
Version: 1.0.1
Summary: Autonomous AI Agent for Self-Healing Code Security
Home-page: https://github.com/gourav-kd/nova-steward
Author: Gourav Kumar Dhaka
Author-email: gauravkr7114@gmail.com
Classifier: Programming Language :: Python :: 3
Classifier: License :: OSI Approved :: MIT License
Classifier: Operating System :: OS Independent
Requires-Python: >=3.6
Dynamic: author
Dynamic: author-email
Dynamic: classifier
Dynamic: description
Dynamic: description-content-type
Dynamic: home-page
Dynamic: requires-python
Dynamic: summary
